mp3/memory.sv
// Memory module

module memory #(
    parameter INIT_FILE = ""
) (
    input logic clk,
    input logic [6:0] addr,
    output logic [9:0] data
);
  logic [9:0] mem[0:128];

  initial begin
    if (INIT_FILE != "") begin
      $readmemh(INIT_FILE, mem);
    end
  end

  assign data = mem[addr];

endmodule

mp3/fsm.sv
// FSM for the 4 sine wave states
`include "memory.sv"

module fsm #(
    parameter MEM_SIZE  = 128,
    parameter SINE_PATH = ""
) (
    input logic clk,
    output logic [9:0] out
);

  typedef enum logic [1:0] {
    SINE_1,
    SINE_2,
    SINE_3,
    SINE_4
  } state_t;

  logic [1:0] current_state;
  logic [1:0] next_state;
  logic [6:0] addr;
  logic [9:0] mem_out;
  logic [6:0] counter;
  logic time_to_change;

  initial begin
    current_state = SINE_1;
    addr = 0;
    counter = 0;
    time_to_change = 0;
  end

  memory #(
      .INIT_FILE(SINE_PATH)
  ) mem (
      .clk (clk),
      .addr(addr),
      .data(mem_out)
  );

  always_ff @(posedge clk) begin
    // advance the memory address
    case (current_state)
      SINE_1: begin
        out  <= mem_out;
        addr <= addr + 1;
      end
      SINE_2: begin
        out  <= mem_out;
        addr <= addr - 1;
      end
      SINE_3: begin
        out  <= 1024 - mem_out;
        addr <= addr + 1;
      end
      SINE_4: begin
        out  <= 1024 - mem_out;
        addr <= addr - 1;
      end
      default: begin
        out  <= 0;
        addr <= 0;
      end
    endcase

    counter <= counter + 1;
    if (counter == MEM_SIZE - 2) begin
      time_to_change <= 1;
    end
  end

  always_ff @(posedge clk) begin
    if (time_to_change == 1) begin
      case (current_state)
        SINE_1: begin
          current_state <= 2'b01;
          addr <= MEM_SIZE - 1;
          time_to_change <= 0;
        end
        SINE_2: begin
          current_state <= 2'b10;
          addr <= 0;
          time_to_change <= 0;
        end
        SINE_3: begin
          current_state <= 2'b11;
          addr <= MEM_SIZE - 1;
          time_to_change <= 0;
        end
        default: begin
          current_state <= 2'b00;
          addr <= 0;
          time_to_change <= 0;
        end
      endcase

      time_to_change <= 0;
    end
  end
endmodule

mp3/sine.sv
`include "fsm.sv"

module top (
    input  logic clk,
    output logic _9b,   // D0
    output logic _6a,   // D1
    output logic _4a,   // D2
    output logic _2a,   // D3
    output logic _0a,   // D4
    output logic _5a,   // D5
    output logic _3b,   // D6
    output logic _49a,  // D7
    output logic _45a,  // D8
    output logic _48b   // D9
);

  logic [9:0] data;

  fsm #(
      .MEM_SIZE (128),
      .SINE_PATH("sine.txt")
  ) wavegen (
      .clk(clk),
      .out(data)
  );


  assign {_48b, _45a, _49a, _3b, _5a, _0a, _2a, _4a, _6a, _9b} = data;

endmodule

mp3/sine_tb.sv
`timescale 10ns / 10ns
`include "sine.sv"

module sine_tb;

  logic clk = 0;
  logic _9b, _6a, _4a, _2a, _0a, _5a, _3b, _49a, _45a, _48b;

  top u0 (
      .clk (clk),
      ._9b (_9b),
      ._6a (_6a),
      ._4a (_4a),
      ._2a (_2a),
      ._0a (_0a),
      ._5a (_5a),
      ._3b (_3b),
      ._49a(_49a),
      ._45a(_45a),
      ._48b(_48b)
  );

  initial begin
    $dumpfile("sine.vcd");
    $dumpvars(0, sine_tb);
    #10000 $finish;
  end

  always begin
    #4 clk = ~clk;
  end

endmodule

mp3/sine.vcd
$date
	Tue Mar 11 11:40:21 2025
$end
$version
	Icarus Verilog
$end
$timescale
	10ns
$end
$scope module sine_tb $end
$var wire 1 ! _9b $end
$var wire 1 " _6a $end
$var wire 1 # _5a $end
$var wire 1 $ _4a $end
$var wire 1 % _49a $end
$var wire 1 & _48b $end
$var wire 1 ' _45a $end
$var wire 1 ( _3b $end
$var wire 1 ) _2a $end
$var wire 1 * _0a $end
$var reg 1 + clk $end
$scope module u0 $end
$var wire 1 + clk $end
$var wire 10 , data [9:0] $end
$var wire 1 ! _9b $end
$var wire 1 " _6a $end
$var wire 1 # _5a $end
$var wire 1 $ _4a $end
$var wire 1 % _49a $end
$var wire 1 & _48b $end
$var wire 1 ' _45a $end
$var wire 1 ( _3b $end
$var wire 1 ) _2a $end
$var wire 1 * _0a $end
$scope module wavegen $end
$var wire 1 + clk $end
$var wire 10 - mem_out [9:0] $end
$var parameter 32 . MEM_SIZE $end
$var parameter 64 / SINE_PATH $end
$var reg 7 0 addr [6:0] $end
$var reg 7 1 counter [6:0] $end
$var reg 2 2 current_state [1:0] $end
$var reg 10 3 out [9:0] $end
$var reg 1 4 time_to_change $end
$scope module mem $end
$var wire 7 5 addr [6:0] $end
$var wire 1 + clk $end
$var wire 10 6 data [9:0] $end
$var parameter 64 7 INIT_FILE $end
$upscope $end
$upscope $end
$upscope $end
$upscope $end
$enddefinitions $end
$comment Show the parameter values. $end
$dumpall
b111001101101001011011100110010100101110011101000111100001110100 7
b111001101101001011011100110010100101110011101000111100001110100 /
b10000000 .
$end
#0
$dumpvars
b1000000000 6
b0 5
04
bx 3
b0 2
b0 1
b0 0
b1000000000 -
bx ,
0+
x*
x)
x(
x'
x&
x%
x$
x#
x"
x!
$end
#4
b1000000110 -
b1000000110 6
1&
0'
0%
0(
0#
0*
0)
0$
0"
0!
b1 1
b1 0
b1 5
b1000000000 ,
b1000000000 3
1+
#8
0+
#12
b1000001100 -
b1000001100 6
1$
1"
b10 1
b10 0
b10 5
b1000000110 ,
b1000000110 3
1+
#16
0+
#20
b1000010010 -
b1000010010 6
1)
0"
b11 1
b11 0
b11 5
b1000001100 ,
b1000001100 3
1+
#24
0+
#28
b1000011001 -
b1000011001 6
1*
0)
0$
1"
b100 1
b100 0
b100 5
b1000010010 ,
b1000010010 3
1+
#32
0+
#36
b1000011111 -
b1000011111 6
1)
0"
1!
b101 1
b101 0
b101 5
b1000011001 ,
b1000011001 3
1+
#40
0+
#44
b1000100101 -
b1000100101 6
1$
1"
b110 1
b110 0
b110 5
b1000011111 ,
b1000011111 3
1+
#48
0+
#52
b1000101011 -
b1000101011 6
1#
0*
0)
0"
b111 1
b111 0
b111 5
b1000100101 ,
b1000100101 3
1+
#56
0+
#60
b1000110010 -
b1000110010 6
1)
0$
1"
b1000 1
b1000 0
b1000 5
b1000101011 ,
b1000101011 3
1+
#64
0+
#68
b1000111000 -
b1000111000 6
1*
0)
0!
b1001 1
b1001 0
b1001 5
b1000110010 ,
b1000110010 3
1+
#72
0+
#76
b1000111110 -
b1000111110 6
1)
0"
b1010 1
b1010 0
b1010 5
b1000111000 ,
b1000111000 3
1+
#80
0+
#84
b1001000100 -
b1001000100 6
1$
1"
b1011 1
b1011 0
b1011 5
b1000111110 ,
b1000111110 3
1+
#88
0+
#92
b1001001011 -
b1001001011 6
1(
0#
0*
0)
0"
b1100 1
b1100 0
b1100 5
b1001000100 ,
b1001000100 3
1+
#96
0+
#100
b1001010001 -
b1001010001 6
1)
0$
1"
1!
b1101 1
b1101 0
b1101 5
b1001001011 ,
b1001001011 3
1+
#104
0+
#108
b1001010111 -
b1001010111 6
1*
0)
0"
b1110 1
b1110 0
b1110 5
b1001010001 ,
b1001010001 3
1+
#112
0+
#116
b1001011101 -
b1001011101 6
1$
1"
b1111 1
b1111 0
b1111 5
b1001010111 ,
b1001010111 3
1+
#120
0+
#124
b1001100011 -
b1001100011 6
1)
0"
b10000 1
b10000 0
b10000 5
b1001011101 ,
b1001011101 3
1+
#128
0+
#132
b1001101001 -
b1001101001 6
1#
0*
0)
0$
1"
b10001 1
b10001 0
b10001 5
b1001100011 ,
b1001100011 3
1+
#136
0+
#140
b1001110000 -
b1001110000 6
1)
0"
b10010 1
b10010 0
b10010 5
b1001101001 ,
b1001101001 3
1+
#144
0+
#148
b1001110110 -
b1001110110 6
1*
0)
0!
b10011 1
b10011 0
b10011 5
b1001110000 ,
b1001110000 3
1+
#152
0+
#156
b1001111100 -
b1001111100 6
1$
1"
b10100 1
b10100 0
b10100 5
b1001110110 ,
b1001110110 3
1+
#160
0+
#164
b1010000010 -
b1010000010 6
1)
0"
b10101 1
b10101 0
b10101 5
b1001111100 ,
b1001111100 3
1+
#168
0+
#172
b1010001000 -
b1010001000 6
1%
0(
0#
0*
0)
0$
1"
b10110 1
b10110 0
b10110 5
b1010000010 ,
b1010000010 3
1+
#176
0+
#180
b1010001110 -
b1010001110 6
1)
0"
b10111 1
b10111 0
b10111 5
b1010001000 ,
b1010001000 3
1+
#184
0+
#188
b1010010100 -
b1010010100 6
1$
1"
b11000 1
b11000 0
b11000 5
b1010001110 ,
b1010001110 3
1+
#192
0+
#196
b1010011010 -
b1010011010 6
1*
0)
0"
b11001 1
b11001 0
b11001 5
b1010010100 ,
b1010010100 3
1+
#200
0+
#204
b1010100000 -
b1010100000 6
1)
0$
1"
b11010 1
b11010 0
b11010 5
b1010011010 ,
b1010011010 3
1+
#208
0+
#212
b1010100110 -
b1010100110 6
1#
0*
0)
0"
b11011 1
b11011 0
b11011 5
b1010100000 ,
b1010100000 3
1+
#216
0+
#220
b1010101100 -
b1010101100 6
1$
1"
b11100 1
b11100 0
b11100 5
b1010100110 ,
b1010100110 3
1+
#224
0+
#228
b1010110010 -
b1010110010 6
1)
0"
b11101 1
b11101 0
b11101 5
b1010101100 ,
b1010101100 3
1+
#232
0+
#236
b1010111000 -
b1010111000 6
1*
0)
0$
1"
b11110 1
b11110 0
b11110 5
b1010110010 ,
b1010110010 3
1+
#240
0+
#244
b1010111101 -
b1010111101 6
1)
0"
b11111 1
b11111 0
b11111 5
b1010111000 ,
b1010111000 3
1+
#248
0+
#252
b1011000011 -
b1011000011 6
1$
1!
b100000 1
b100000 0
b100000 5
b1010111101 ,
b1010111101 3
1+
#256
0+
#260
b1011001001 -
b1011001001 6
1(
0#
0*
0)
0$
1"
b100001 1
b100001 0
b100001 5
b1011000011 ,
b1011000011 3
1+
#264
0+
#268
b1011001111 -
b1011001111 6
1)
0"
b100010 1
b100010 0
b100010 5
b1011001001 ,
b1011001001 3
1+
#272
0+
#276
b1011010101 -
b1011010101 6
1$
1"
b100011 1
b100011 0
b100011 5
b1011001111 ,
b1011001111 3
1+
#280
0+
#284
b1011011010 -
b1011011010 6
1*
0)
0"
b100100 1
b100100 0
b100100 5
b1011010101 ,
b1011010101 3
1+
#288
0+
#292
b1011100000 -
b1011100000 6
1)
0$
1"
0!
b100101 1
b100101 0
b100101 5
b1011011010 ,
b1011011010 3
1+
#296
0+
#300
b1011100101 -
b1011100101 6
1#
0*
0)
0"
b100110 1
b100110 0
b100110 5
b1011100000 ,
b1011100000 3
1+
#304
0+
#308
b1011101011 -
b1011101011 6
1$
1!
b100111 1
b100111 0
b100111 5
b1011100101 ,
b1011100101 3
1+
#312
0+
#316
b1011110001 -
b1011110001 6
1)
0$
1"
b101000 1
b101000 0
b101000 5
b1011101011 ,
b1011101011 3
1+
#320
0+
#324
b1011110110 -
b1011110110 6
1*
0)
0"
b101001 1
b101001 0
b101001 5
b1011110001 ,
b1011110001 3
1+
#328
0+
#332
b1011111100 -
b1011111100 6
1$
1"
0!
b101010 1
b101010 0
b101010 5
b1011110110 ,
b1011110110 3
1+
#336
0+
#340
b1100000001 -
b1100000001 6
1)
0"
b101011 1
b101011 0
b101011 5
b1011111100 ,
b1011111100 3
1+
#344
0+
#348
b1100000110 -
b1100000110 6
1'
0%
0(
0#
0*
0)
0$
1!
b101100 1
b101100 0
b101100 5
b1100000001 ,
b1100000001 3
1+
#352
0+
#356
b1100001100 -
b1100001100 6
1$
1"
0!
b101101 1
b101101 0
b101101 5
b1100000110 ,
b1100000110 3
1+
#360
0+
#364
b1100010001 -
b1100010001 6
1)
0"
b101110 1
b101110 0
b101110 5
b1100001100 ,
b1100001100 3
1+
#368
0+
#372
b1100010110 -
b1100010110 6
1*
0)
0$
1!
b101111 1
b101111 0
b101111 5
b1100010001 ,
b1100010001 3
1+
#376
0+
#380
b1100011100 -
b1100011100 6
1$
1"
0!
b110000 1
b110000 0
b110000 5
b1100010110 ,
b1100010110 3
1+
#384
0+
#388
b1100100001 -
b1100100001 6
1)
0"
b110001 1
b110001 0
b110001 5
b1100011100 ,
b1100011100 3
1+
#392
0+
#396
b1100100110 -
b1100100110 6
1#
0*
0)
0$
1!
b110010 1
b110010 0
b110010 5
b1100100001 ,
b1100100001 3
1+
#400
0+
#404
b1100101011 -
b1100101011 6
1$
1"
0!
b110011 1
b110011 0
b110011 5
b1100100110 ,
b1100100110 3
1+
#408
0+
#412
b1100110000 -
b1100110000 6
1)
0$
1!
b110100 1
b110100 0
b110100 5
b1100101011 ,
b1100101011 3
1+
#416
0+
#420
b1100110101 -
b1100110101 6
1*
0)
0"
0!
b110101 1
b110101 0
b110101 5
b1100110000 ,
b1100110000 3
1+
#424
0+
#428
b1100111010 -
b1100111010 6
1$
1!
b110110 1
b110110 0
b110110 5
b1100110101 ,
b1100110101 3
1+
#432
0+
#436
b1100111111 -
b1100111111 6
1)
0$
1"
0!
b110111 1
b110111 0
b110111 5
b1100111010 ,
b1100111010 3
1+
#440
0+
#444
b1101000100 -
b1101000100 6
1$
1!
b111000 1
b111000 0
b111000 5
b1100111111 ,
b1100111111 3
1+
#448
0+
#452
b1101001001 -
b1101001001 6
1(
0#
0*
0)
0"
0!
b111001 1
b111001 0
b111001 5
b1101000100 ,
b1101000100 3
1+
#456
0+
#460
b1101001110 -
b1101001110 6
1)
0$
1!
b111010 1
b111010 0
b111010 5
b1101001001 ,
b1101001001 3
1+
#464
0+
#468
b1101010010 -
b1101010010 6
1$
1"
0!
b111011 1
b111011 0
b111011 5
b1101001110 ,
b1101001110 3
1+
#472
0+
#476
b1101010111 -
b1101010111 6
1*
0)
0$
b111100 1
b111100 0
b111100 5
b1101010010 ,
b1101010010 3
1+
#480
0+
#484
b1101011100 -
b1101011100 6
1$
1!
b111101 1
b111101 0
b111101 5
b1101010111 ,
b1101010111 3
1+
#488
0+
#492
b1101100000 -
b1101100000 6
1)
0"
0!
b111110 1
b111110 0
b111110 5
b1101011100 ,
b1101011100 3
1+
#496
0+
#500
b1101100101 -
b1101100101 6
1#
0*
0)
0$
b111111 1
b111111 0
b111111 5
b1101100000 ,
b1101100000 3
1+
#504
0+
#508
b1101101001 -
b1101101001 6
1$
1!
b1000000 1
b1000000 0
b1000000 5
b1101100101 ,
b1101100101 3
1+
#512
0+
#516
b1101101110 -
b1101101110 6
1)
0$
b1000001 1
b1000001 0
b1000001 5
b1101101001 ,
b1101101001 3
1+
#520
0+
#524
b1101110010 -
b1101110010 6
1$
1"
0!
b1000010 1
b1000010 0
b1000010 5
b1101101110 ,
b1101101110 3
1+
#528
0+
#532
b1101110110 -
b1101110110 6
1*
0)
0$
b1000011 1
b1000011 0
b1000011 5
b1101110010 ,
b1101110010 3
1+
#536
0+
#540
b1101111010 -
b1101111010 6
1$
b1000100 1
b1000100 0
b1000100 5
b1101110110 ,
b1101110110 3
1+
#544
0+
#548
b1101111111 -
b1101111111 6
1)
0$
b1000101 1
b1000101 0
b1000101 5
b1101111010 ,
b1101111010 3
1+
#552
0+
#556
b1110000011 -
b1110000011 6
1$
1!
b1000110 1
b1000110 0
b1000110 5
b1101111111 ,
b1101111111 3
1+
#560
0+
#564
b1110000111 -
b1110000111 6
1%
0(
0#
0*
0)
0$
b1000111 1
b1000111 0
b1000111 5
b1110000011 ,
b1110000011 3
1+
#568
0+
#572
b1110001011 -
b1110001011 6
1$
b1001000 1
b1001000 0
b1001000 5
b1110000111 ,
b1110000111 3
1+
#576
0+
#580
b1110001111 -
b1110001111 6
1)
0$
b1001001 1
b1001001 0
b1001001 5
b1110001011 ,
b1110001011 3
1+
#584
0+
#588
b1110010011 -
b1110010011 6
1$
b1001010 1
b1001010 0
b1001010 5
b1110001111 ,
b1110001111 3
1+
#592
0+
#596
b1110010111 -
b1110010111 6
1*
0)
0$
b1001011 1
b1001011 0
b1001011 5
b1110010011 ,
b1110010011 3
1+
#600
0+
#604
b1110011010 -
b1110011010 6
1$
b1001100 1
b1001100 0
b1001100 5
b1110010111 ,
b1110010111 3
1+
#608
0+
#612
b1110011110 -
b1110011110 6
1)
0$
0!
b1001101 1
b1001101 0
b1001101 5
b1110011010 ,
b1110011010 3
1+
#616
0+
#620
b1110100010 -
b1110100010 6
1$
b1001110 1
b1001110 0
b1001110 5
b1110011110 ,
b1110011110 3
1+
#624
0+
#628
b1110100101 -
b1110100101 6
1#
0*
0)
0$
b1001111 1
b1001111 0
b1001111 5
b1110100010 ,
b1110100010 3
1+
#632
0+
#636
b1110101001 -
b1110101001 6
1$
0"
1!
b1010000 1
b1010000 0
b1010000 5
b1110100101 ,
b1110100101 3
1+
#640
0+
#644
b1110101100 -
b1110101100 6
1)
0$
b1010001 1
b1010001 0
b1010001 5
b1110101001 ,
b1110101001 3
1+
#648
0+
#652
b1110110000 -
b1110110000 6
1$
0!
b1010010 1
b1010010 0
b1010010 5
b1110101100 ,
b1110101100 3
1+
#656
0+
#660
b1110110011 -
b1110110011 6
1*
0)
0$
b1010011 1
b1010011 0
b1010011 5
b1110110000 ,
b1110110000 3
1+
#664
0+
#668
b1110110110 -
b1110110110 6
1"
1!
b1010100 1
b1010100 0
b1010100 5
b1110110011 ,
b1110110011 3
1+
#672
0+
#676
b1110111001 -
b1110111001 6
1$
0!
b1010101 1
b1010101 0
b1010101 5
b1110110110 ,
b1110110110 3
1+
#680
0+
#684
b1110111101 -
b1110111101 6
1)
0$
0"
1!
b1010110 1
b1010110 0
b1010110 5
b1110111001 ,
b1110111001 3
1+
#688
0+
#692
b1111000000 -
b1111000000 6
1$
b1010111 1
b1010111 0
b1010111 5
b1110111101 ,
b1110111101 3
1+
#696
0+
#700
b1111000011 -
b1111000011 6
1(
0#
0*
0)
0$
0!
b1011000 1
b1011000 0
b1011000 5
b1111000000 ,
b1111000000 3
1+
#704
0+
#708
b1111000110 -
b1111000110 6
1"
1!
b1011001 1
b1011001 0
b1011001 5
b1111000011 ,
b1111000011 3
1+
#712
0+
#716
b1111001000 -
b1111001000 6
1$
0!
b1011010 1
b1011010 0
b1011010 5
b1111000110 ,
b1111000110 3
1+
#720
0+
#724
b1111001011 -
b1111001011 6
1)
0$
0"
b1011011 1
b1011011 0
b1011011 5
b1111001000 ,
b1111001000 3
1+
#728
0+
#732
b1111001110 -
b1111001110 6
1"
1!
b1011100 1
b1011100 0
b1011100 5
b1111001011 ,
b1111001011 3
1+
#736
0+
#740
b1111010001 -
b1111010001 6
1$
0!
b1011101 1
b1011101 0
b1011101 5
b1111001110 ,
b1111001110 3
1+
#744
0+
#748
b1111010011 -
b1111010011 6
1*
0)
0$
0"
1!
b1011110 1
b1011110 0
b1011110 5
b1111010001 ,
b1111010001 3
1+
#752
0+
#756
b1111010110 -
b1111010110 6
1"
b1011111 1
b1011111 0
b1011111 5
b1111010011 ,
b1111010011 3
1+
#760
0+
#764
b1111011000 -
b1111011000 6
1$
0!
b1100000 1
b1100000 0
b1100000 5
b1111010110 ,
b1111010110 3
1+
#768
0+
#772
b1111011010 -
b1111011010 6
1)
0$
0"
b1100001 1
b1100001 0
b1100001 5
b1111011000 ,
b1111011000 3
1+
#776
0+
#780
b1111011101 -
b1111011101 6
1"
b1100010 1
b1100010 0
b1100010 5
b1111011010 ,
b1111011010 3
1+
#784
0+
#788
b1111011111 -
b1111011111 6
1$
0"
1!
b1100011 1
b1100011 0
b1100011 5
b1111011101 ,
b1111011101 3
1+
#792
0+
#796
b1111100001 -
b1111100001 6
1"
b1100100 1
b1100100 0
b1100100 5
b1111011111 ,
b1111011111 3
1+
#800
0+
#804
b1111100011 -
b1111100011 6
1#
0*
0)
0$
0"
b1100101 1
b1100101 0
b1100101 5
b1111100001 ,
b1111100001 3
1+
#808
0+
#812
b1111100101 -
b1111100101 6
1"
b1100110 1
b1100110 0
b1100110 5
b1111100011 ,
b1111100011 3
1+
#816
0+
#820
b1111100111 -
b1111100111 6
1$
0"
b1100111 1
b1100111 0
b1100111 5
b1111100101 ,
b1111100101 3
1+
#824
0+
#828
b1111101001 -
b1111101001 6
1"
b1101000 1
b1101000 0
b1101000 5
b1111100111 ,
b1111100111 3
1+
#832
0+
#836
b1111101011 -
b1111101011 6
1)
0$
0"
b1101001 1
b1101001 0
b1101001 5
b1111101001 ,
b1111101001 3
1+
#840
0+
#844
b1111101100 -
b1111101100 6
1"
b1101010 1
b1101010 0
b1101010 5
b1111101011 ,
b1111101011 3
1+
#848
0+
#852
b1111101110 -
b1111101110 6
1$
0"
0!
b1101011 1
b1101011 0
b1101011 5
b1111101100 ,
b1111101100 3
1+
#856
0+
#860
b1111110000 -
b1111110000 6
1"
b1101100 1
b1101100 0
b1101100 5
b1111101110 ,
b1111101110 3
1+
#864
0+
#868
b1111110001 -
b1111110001 6
1*
0)
0$
0"
b1101101 1
b1101101 0
b1101101 5
b1111110000 ,
b1111110000 3
1+
#872
0+
#876
b1111110011 -
b1111110011 6
1!
b1101110 1
b1101110 0
b1101110 5
b1111110001 ,
b1111110001 3
1+
#880
0+
#884
b1111110100 -
b1111110100 6
1"
b1101111 1
b1101111 0
b1101111 5
b1111110011 ,
b1111110011 3
1+
#888
0+
#892
b1111110101 -
b1111110101 6
1$
0"
0!
b1110000 1
b1110000 0
b1110000 5
b1111110100 ,
b1111110100 3
1+
#896
0+
#900
b1111110110 -
b1111110110 6
1!
b1110001 1
b1110001 0
b1110001 5
b1111110101 ,
b1111110101 3
1+
#904
0+
#908
b1111110111 -
b1111110111 6
1"
0!
b1110010 1
b1110010 0
b1110010 5
b1111110110 ,
b1111110110 3
1+
#912
0+
#916
b1111111001 -
b1111111001 6
1!
b1110011 1
b1110011 0
b1110011 5
b1111110111 ,
b1111110111 3
1+
#920
0+
#924
1)
0$
0"
b1110100 1
b1110100 0
b1110100 5
b1111111001 ,
b1111111001 3
1+
#928
0+
#932
b1111111010 -
b1111111010 6
b1110101 1
b1110101 0
b1110101 5
1+
#936
0+
#940
b1111111011 -
b1111111011 6
1"
0!
b1110110 1
b1110110 0
b1110110 5
b1111111010 ,
b1111111010 3
1+
#944
0+
#948
b1111111100 -
b1111111100 6
1!
b1110111 1
b1110111 0
b1110111 5
b1111111011 ,
b1111111011 3
1+
#952
0+
#956
b1111111101 -
b1111111101 6
1$
0"
0!
b1111000 1
b1111000 0
b1111000 5
b1111111100 ,
b1111111100 3
1+
#960
0+
#964
1!
b1111001 1
b1111001 0
b1111001 5
b1111111101 ,
b1111111101 3
1+
#968
0+
#972
b1111111110 -
b1111111110 6
b1111010 1
b1111010 0
b1111010 5
1+
#976
0+
#980
1"
0!
b1111011 1
b1111011 0
b1111011 5
b1111111110 ,
b1111111110 3
1+
#984
0+
#988
b1111100 1
b1111100 0
b1111100 5
1+
#992
0+
#996
b1111111111 -
b1111111111 6
b1111101 1
b1111101 0
b1111101 5
1+
#1000
0+
#1004
1!
b1111110 1
b1111110 0
b1111110 5
b1111111111 ,
b1111111111 3
1+
#1008
0+
#1012
14
b1111111 1
b1111111 0
b1111111 5
1+
#1016
0+
#1020
04
b1 2
b0 1
b1111111 0
b1111111 5
1+
#1024
0+
#1028
b1 1
b1111110 0
b1111110 5
1+
#1032
0+
#1036
b10 1
b1111101 0
b1111101 5
1+
#1040
0+
#1044
b1111111110 -
b1111111110 6
b11 1
b1111100 0
b1111100 5
1+
#1048
0+
#1052
0!
b100 1
b1111011 0
b1111011 5
b1111111110 ,
b1111111110 3
1+
#1056
0+
#1060
b101 1
b1111010 0
b1111010 5
1+
#1064
0+
#1068
b1111111101 -
b1111111101 6
b110 1
b1111001 0
b1111001 5
1+
#1072
0+
#1076
0"
1!
b111 1
b1111000 0
b1111000 5
b1111111101 ,
b1111111101 3
1+
#1080
0+
#1084
b1111111100 -
b1111111100 6
b1000 1
b1110111 0
b1110111 5
1+
#1088
0+
#1092
b1111111011 -
b1111111011 6
0!
b1001 1
b1110110 0
b1110110 5
b1111111100 ,
b1111111100 3
1+
#1096
0+
#1100
b1111111010 -
b1111111010 6
0$
1"
1!
b1010 1
b1110101 0
b1110101 5
b1111111011 ,
b1111111011 3
1+
#1104
0+
#1108
b1111111001 -
b1111111001 6
0!
b1011 1
b1110100 0
b1110100 5
b1111111010 ,
b1111111010 3
1+
#1112
0+
#1116
0"
1!
b1100 1
b1110011 0
b1110011 5
b1111111001 ,
b1111111001 3
1+
#1120
0+
#1124
b1111110111 -
b1111110111 6
b1101 1
b1110010 0
b1110010 5
1+
#1128
0+
#1132
b1111110110 -
b1111110110 6
0)
1$
1"
b1110 1
b1110001 0
b1110001 5
b1111110111 ,
b1111110111 3
1+
#1136
0+
#1140
b1111110101 -
b1111110101 6
0!
b1111 1
b1110000 0
b1110000 5
b1111110110 ,
b1111110110 3
1+
#1144
0+
#1148
b1111110100 -
b1111110100 6
0"
1!
b10000 1
b1101111 0
b1101111 5
b1111110101 ,
b1111110101 3
1+
#1152
0+
#1156
b1111110011 -
b1111110011 6
0!
b10001 1
b1101110 0
b1101110 5
b1111110100 ,
b1111110100 3
1+
#1160
0+
#1164
b1111110001 -
b1111110001 6
0$
1"
1!
b10010 1
b1101101 0
b1101101 5
b1111110011 ,
b1111110011 3
1+
#1168
0+
#1172
b1111110000 -
b1111110000 6
0"
b10011 1
b1101100 0
b1101100 5
b1111110001 ,
b1111110001 3
1+
#1176
0+
#1180
b1111101110 -
b1111101110 6
0!
b10100 1
b1101011 0
b1101011 5
b1111110000 ,
b1111110000 3
1+
#1184
0+
#1188
b1111101100 -
b1111101100 6
0*
1)
1$
1"
b10101 1
b1101010 0
b1101010 5
b1111101110 ,
b1111101110 3
1+
#1192
0+
#1196
b1111101011 -
b1111101011 6
0"
b10110 1
b1101001 0
b1101001 5
b1111101100 ,
b1111101100 3
1+
#1200
0+
#1204
b1111101001 -
b1111101001 6
0$
1"
1!
b10111 1
b1101000 0
b1101000 5
b1111101011 ,
b1111101011 3
1+
#1208
0+
#1212
b1111100111 -
b1111100111 6
0"
b11000 1
b1100111 0
b1100111 5
b1111101001 ,
b1111101001 3
1+
#1216
0+
#1220
b1111100101 -
b1111100101 6
0)
1$
1"
b11001 1
b1100110 0
b1100110 5
b1111100111 ,
b1111100111 3
1+
#1224
0+
#1228
b1111100011 -
b1111100011 6
0"
b11010 1
b1100101 0
b1100101 5
b1111100101 ,
b1111100101 3
1+
#1232
0+
#1236
b1111100001 -
b1111100001 6
0$
1"
b11011 1
b1100100 0
b1100100 5
b1111100011 ,
b1111100011 3
1+
#1240
0+
#1244
b1111011111 -
b1111011111 6
0"
b11100 1
b1100011 0
b1100011 5
b1111100001 ,
b1111100001 3
1+
#1248
0+
#1252
b1111011101 -
b1111011101 6
0#
1*
1)
1$
1"
b11101 1
b1100010 0
b1100010 5
b1111011111 ,
b1111011111 3
1+
#1256
0+
#1260
b1111011010 -
b1111011010 6
0"
b11110 1
b1100001 0
b1100001 5
b1111011101 ,
b1111011101 3
1+
#1264
0+
#1268
b1111011000 -
b1111011000 6
0$
1"
0!
b11111 1
b1100000 0
b1100000 5
b1111011010 ,
b1111011010 3
1+
#1272
0+
#1276
b1111010110 -
b1111010110 6
0"
b100000 1
b1011111 0
b1011111 5
b1111011000 ,
b1111011000 3
1+
#1280
0+
#1284
b1111010011 -
b1111010011 6
0)
1$
1"
b100001 1
b1011110 0
b1011110 5
b1111010110 ,
b1111010110 3
1+
#1288
0+
#1292
b1111010001 -
b1111010001 6
0$
1!
b100010 1
b1011101 0
b1011101 5
b1111010011 ,
b1111010011 3
1+
#1296
0+
#1300
b1111001110 -
b1111001110 6
0"
b100011 1
b1011100 0
b1011100 5
b1111010001 ,
b1111010001 3
1+
#1304
0+
#1308
b1111001011 -
b1111001011 6
0*
1)
1$
1"
0!
b100100 1
b1011011 0
b1011011 5
b1111001110 ,
b1111001110 3
1+
#1312
0+
#1316
b1111001000 -
b1111001000 6
0$
1!
b100101 1
b1011010 0
b1011010 5
b1111001011 ,
b1111001011 3
1+
#1320
0+
#1324
b1111000110 -
b1111000110 6
0"
0!
b100110 1
b1011001 0
b1011001 5
b1111001000 ,
b1111001000 3
1+
#1328
0+
#1332
b1111000011 -
b1111000011 6
0)
1$
1"
b100111 1
b1011000 0
b1011000 5
b1111000110 ,
b1111000110 3
1+
#1336
0+
#1340
b1111000000 -
b1111000000 6
0$
1!
b101000 1
b1010111 0
b1010111 5
b1111000011 ,
b1111000011 3
1+
#1344
0+
#1348
b1110111101 -
b1110111101 6
0"
0!
b101001 1
b1010110 0
b1010110 5
b1111000000 ,
b1111000000 3
1+
#1352
0+
#1356
b1110111001 -
b1110111001 6
0(
1#
1*
1)
1$
1!
b101010 1
b1010101 0
b1010101 5
b1110111101 ,
b1110111101 3
1+
#1360
0+
#1364
b1110110110 -
b1110110110 6
0$
b101011 1
b1010100 0
b1010100 5
b1110111001 ,
b1110111001 3
1+
#1368
0+
#1372
b1110110011 -
b1110110011 6
0)
1$
1"
0!
b101100 1
b1010011 0
b1010011 5
b1110110110 ,
b1110110110 3
1+
#1376
0+
#1380
b1110110000 -
b1110110000 6
0$
1!
b101101 1
b1010010 0
b1010010 5
b1110110011 ,
b1110110011 3
1+
#1384
0+
#1388
b1110101100 -
b1110101100 6
0"
0!
b101110 1
b1010001 0
b1010001 5
b1110110000 ,
b1110110000 3
1+
#1392
0+
#1396
b1110101001 -
b1110101001 6
0*
1)
1$
b101111 1
b1010000 0
b1010000 5
b1110101100 ,
b1110101100 3
1+
#1400
0+
#1404
b1110100101 -
b1110100101 6
0$
1!
b110000 1
b1001111 0
b1001111 5
b1110101001 ,
b1110101001 3
1+
#1408
0+
#1412
b1110100010 -
b1110100010 6
0)
1$
b110001 1
b1001110 0
b1001110 5
b1110100101 ,
b1110100101 3
1+
#1416
0+
#1420
b1110011110 -
b1110011110 6
0$
1"
0!
b110010 1
b1001101 0
b1001101 5
b1110100010 ,
b1110100010 3
1+
#1424
0+
